gitpt/cli.py
gitpt/generators/__init__.py
gitpt/generators/comments.py
gitpt/prompts/prompt_message.md
gitpt/prompts/prompt_summary.md
gitpt/prompts/small_prompt.md
gitpt/prompts/verbose_prompt.md
gitpt/utils/__init__.py
gitpt/utils/config.py
gitpt/utils/spinner.py
gitpt-0.2.0.dist-info/METADATA
gitpt-0.2.0.dist-info/WHEEL
gitpt-0.2.0.dist-info/entry_points.txt
gitpt-0.2.0.dist-info/RECORD
