Metadata-Version: 2.1
Name: gitpt
Version: 0.2.0
Summary: An LLM based git commit message creator.
Author: Your Name
Author-email: you@example.com
Requires-Python: >=3.10,<4.0
Classifier: Programming Language :: Python :: 3
Classifier: Programming Language :: Python :: 3.10
Classifier: Programming Language :: Python :: 3.11
Classifier: Programming Language :: Python :: 3.12
Classifier: Programming Language :: Python :: 3.13
Requires-Dist: click (>=8.1)
Requires-Dist: langchain-anthropic (>=0.2.3,<0.3.0)
Requires-Dist: langchain-core (>=0.3.13,<0.4.0)
Requires-Dist: langchain-google-genai (>=2.0.4,<3.0.0)
Requires-Dist: langchain-ollama (>=0.2.0,<0.3.0)
Requires-Dist: langchain-openai (>=0.2.4,<0.3.0)
Requires-Dist: tomli (>=2.0.2,<3.0.0)
